card_forge-0.3.0.dist-info/licenses/LICENSE
forge/_version.py
forge/cli.py
forge/constant.py
forge/helper.py
forge/models.py
card_forge-0.3.0.dist-info/METADATA
card_forge-0.3.0.dist-info/WHEEL
card_forge-0.3.0.dist-info/entry_points.txt
card_forge-0.3.0.dist-info/top_level.txt
card_forge-0.3.0.dist-info/RECORD
