Metadata-Version: 2.4
Name: card-forge
Version: 0.3.0
Summary: Modern CLI tool for AI character card management - extract, repositorize, and rebuild character cards
Author-email: "Nya Foundation Team (k3scat)" <k3scat@gmail.com>
License-Expression: MIT
Project-URL: Homepage, https://github.com/Nya-Foundation/card-forge
Project-URL: Bug Tracker, https://github.com/Nya-Foundation/card-forge/issues
Classifier: Development Status :: 4 - Beta
Classifier: Intended Audience :: Developers
Classifier: Programming Language :: Python :: 3
Classifier: Programming Language :: Python :: 3.10
Classifier: Programming Language :: Python :: 3.11
Classifier: Programming Language :: Python :: 3.12
Classifier: Programming Language :: Python :: 3.13
Requires-Python: >=3.10
License-File: LICENSE
Requires-Dist: pillow>=11.3.0
Requires-Dist: pydantic>=2.11.9
Requires-Dist: pyyaml>=6.0.3
Dynamic: license-file
